[
  {
    "epoch": 1,
    "n": 10,
    "rewards_path": "data/processed/notagen/reward_exports/large_sft10_cached10_rewards_refactored_20260626/epoch01_rewards.jsonl",
    "total_reward_mean": 1.8050574644535715,
    "total_reward_min": 1.0232730263157896,
    "total_reward_max": 5.724094808377897,
    "parse_reward_mean": 1.0,
    "parse_reward_min": 1.0,
    "parse_reward_max": 1.0,
    "countdown_reward_mean": 0.9757575757575757,
    "countdown_reward_min": 0.9090909090909091,
    "countdown_reward_max": 1.0,
    "line_closure_reward_mean": 0.909375,
    "line_closure_reward_min": 0.8125,
    "line_closure_reward_max": 1.0,
    "bar_token_reward_mean": 0.9875,
    "bar_token_reward_min": 0.9375,
    "bar_token_reward_max": 1.0,
    "meter_alignment_reward_mean": 0.11820871790459765,
    "meter_alignment_reward_min": 0.0,
    "meter_alignment_reward_max": 0.7941176470588235,
    "meter_duration_closeness_reward_mean": 0.3667716261143055,
    "meter_duration_closeness_reward_min": 0.14947089947089948,
    "meter_duration_closeness_reward_max": 0.943627450980392,
    "bar_meter_consistency_reward_mean": 0.15854166666666666,
    "bar_meter_consistency_reward_min": 0.0,
    "bar_meter_consistency_reward_max": 0.84375,
    "bar_count_reward_mean": 0.15625,
    "bar_count_reward_min": 0.0,
    "bar_count_reward_max": 0.84375,
    "root_similarity_reward_mean": 0.14375,
    "root_similarity_reward_min": 0.09375,
    "root_similarity_reward_max": 0.28125,
    "bass_pitch_class_reward_mean": 0.1,
    "bass_pitch_class_reward_min": 0.0625,
    "bass_pitch_class_reward_max": 0.15625,
    "cadence_root_reward_mean": 0.025,
    "cadence_root_reward_min": 0.0,
    "cadence_root_reward_max": 0.25,
    "cadence_bass_reward_mean": 0.175,
    "cadence_bass_reward_min": 0.0,
    "cadence_bass_reward_max": 0.5,
    "observed_stream_lines_mean": 32.0,
    "observed_stream_lines_min": 32.0,
    "observed_stream_lines_max": 32.0,
    "observed_bars_mean": 5.0,
    "observed_bars_min": 0.0,
    "observed_bars_max": 27.0,
    "validated_bars_mean": 5.0,
    "validated_bars_min": 0.0,
    "validated_bars_max": 27.0
  },
  {
    "epoch": 2,
    "n": 10,
    "rewards_path": "data/processed/notagen/reward_exports/large_sft10_cached10_rewards_refactored_20260626/epoch02_rewards.jsonl",
    "total_reward_mean": 1.4511920701497,
    "total_reward_min": 0.9499255952380952,
    "total_reward_max": 3.0006009615384617,
    "parse_reward_mean": 1.0,
    "parse_reward_min": 1.0,
    "parse_reward_max": 1.0,
    "countdown_reward_mean": 1.0,
    "countdown_reward_min": 1.0,
    "countdown_reward_max": 1.0,
    "line_closure_reward_mean": 0.9125,
    "line_closure_reward_min": 0.8125,
    "line_closure_reward_max": 1.0,
    "bar_token_reward_mean": 0.975,
    "bar_token_reward_min": 0.90625,
    "bar_token_reward_max": 1.0,
    "meter_alignment_reward_mean": 0.03491839368685006,
    "meter_alignment_reward_min": 0.0,
    "meter_alignment_reward_max": 0.18461538461538463,
    "meter_duration_closeness_reward_mean": 0.31736659769554576,
    "meter_duration_closeness_reward_min": 0.176984126984127,
    "meter_duration_closeness_reward_max": 0.6507936507936508,
    "bar_meter_consistency_reward_mean": 0.09981321839080459,
    "bar_meter_consistency_reward_min": 0.0,
    "bar_meter_consistency_reward_max": 0.5,
    "bar_count_reward_mean": 0.096875,
    "bar_count_reward_min": 0.0,
    "bar_count_reward_max": 0.5,
    "root_similarity_reward_mean": 0.10655241935483871,
    "root_similarity_reward_min": 0.0625,
    "root_similarity_reward_max": 0.15625,
    "bass_pitch_class_reward_mean": 0.10967741935483871,
    "bass_pitch_class_reward_min": 0.0,
    "bass_pitch_class_reward_max": 0.21875,
    "cadence_root_reward_mean": 0.05,
    "cadence_root_reward_min": 0.0,
    "cadence_root_reward_max": 0.25,
    "cadence_bass_reward_mean": 0.1,
    "cadence_bass_reward_min": 0.0,
    "cadence_bass_reward_max": 0.25,
    "observed_stream_lines_mean": 32.0,
    "observed_stream_lines_min": 32.0,
    "observed_stream_lines_max": 32.0,
    "observed_bars_mean": 3.1,
    "observed_bars_min": 0.0,
    "observed_bars_max": 16.0,
    "validated_bars_mean": 3.1,
    "validated_bars_min": 0.0,
    "validated_bars_max": 16.0
  },
  {
    "epoch": 3,
    "n": 10,
    "rewards_path": "data/processed/notagen/reward_exports/large_sft10_cached10_rewards_refactored_20260626/epoch03_rewards.jsonl",
    "total_reward_mean": 3.3051024022304065,
    "total_reward_min": 0.8892311151079136,
    "total_reward_max": 6.995572916666667,
    "parse_reward_mean": 0.8,
    "parse_reward_min": 0.0,
    "parse_reward_max": 1.0,
    "countdown_reward_mean": 1.0,
    "countdown_reward_min": 1.0,
    "countdown_reward_max": 1.0,
    "line_closure_reward_mean": 0.928125,
    "line_closure_reward_min": 0.875,
    "line_closure_reward_max": 0.96875,
    "bar_token_reward_mean": 0.971875,
    "bar_token_reward_min": 0.9375,
    "bar_token_reward_max": 1.0,
    "meter_alignment_reward_mean": 0.26911273105104455,
    "meter_alignment_reward_min": 0.0,
    "meter_alignment_reward_max": 0.7166666666666667,
    "meter_duration_closeness_reward_mean": 0.47395171126283825,
    "meter_duration_closeness_reward_min": 0.07314148681055155,
    "meter_duration_closeness_reward_max": 0.9388888888888894,
    "bar_meter_consistency_reward_mean": 0.4312403993855607,
    "bar_meter_consistency_reward_min": 0.0,
    "bar_meter_consistency_reward_max": 0.9642857142857143,
    "bar_count_reward_mean": 0.40625,
    "bar_count_reward_min": 0.0,
    "bar_count_reward_max": 0.875,
    "root_similarity_reward_mean": 0.13314794215795328,
    "root_similarity_reward_min": 0.0625,
    "root_similarity_reward_max": 0.1935483870967742,
    "bass_pitch_class_reward_mean": 0.1614154616240267,
    "bass_pitch_class_reward_min": 0.03225806451612903,
    "bass_pitch_class_reward_max": 0.25,
    "cadence_root_reward_mean": 0.08333333333333333,
    "cadence_root_reward_min": 0.0,
    "cadence_root_reward_max": 0.3333333333333333,
    "cadence_bass_reward_mean": 0.2583333333333333,
    "cadence_bass_reward_min": 0.0,
    "cadence_bass_reward_max": 0.5,
    "observed_stream_lines_mean": 32.0,
    "observed_stream_lines_min": 32.0,
    "observed_stream_lines_max": 32.0,
    "observed_bars_mean": 13.0,
    "observed_bars_min": 0.0,
    "observed_bars_max": 28.0,
    "validated_bars_mean": 13.0,
    "validated_bars_min": 0.0,
    "validated_bars_max": 28.0
  },
  {
    "epoch": 4,
    "n": 10,
    "rewards_path": "data/processed/notagen/reward_exports/large_sft10_cached10_rewards_refactored_20260626/epoch04_rewards.jsonl",
    "total_reward_mean": 3.4780930095368663,
    "total_reward_min": 0.5839015151515151,
    "total_reward_max": 7.3853889627659575,
    "parse_reward_mean": 0.9,
    "parse_reward_min": 0.0,
    "parse_reward_max": 1.0,
    "countdown_reward_mean": 1.0,
    "countdown_reward_min": 1.0,
    "countdown_reward_max": 1.0,
    "line_closure_reward_mean": 0.946875,
    "line_closure_reward_min": 0.875,
    "line_closure_reward_max": 1.0,
    "bar_token_reward_mean": 0.965625,
    "bar_token_reward_min": 0.9375,
    "bar_token_reward_max": 1.0,
    "meter_alignment_reward_mean": 0.20733366390482616,
    "meter_alignment_reward_min": 0.0,
    "meter_alignment_reward_max": 0.5531914893617021,
    "meter_duration_closeness_reward_mean": 0.4339257654776621,
    "meter_duration_closeness_reward_min": 0.020202020202020204,
    "meter_duration_closeness_reward_max": 0.6815920398009953,
    "bar_meter_consistency_reward_mean": 0.4646438172043011,
    "bar_meter_consistency_reward_min": 0.0,
    "bar_meter_consistency_reward_max": 1.0,
    "bar_count_reward_mean": 0.446875,
    "bar_count_reward_min": 0.0,
    "bar_count_reward_max": 0.9375,
    "root_similarity_reward_mean": 0.109375,
    "root_similarity_reward_min": 0.09375,
    "root_similarity_reward_max": 0.15625,
    "bass_pitch_class_reward_mean": 0.15625,
    "bass_pitch_class_reward_min": 0.09375,
    "bass_pitch_class_reward_max": 0.3125,
    "cadence_root_reward_mean": 0.05,
    "cadence_root_reward_min": 0.0,
    "cadence_root_reward_max": 0.25,
    "cadence_bass_reward_mean": 0.375,
    "cadence_bass_reward_min": 0.0,
    "cadence_bass_reward_max": 0.75,
    "observed_stream_lines_mean": 32.0,
    "observed_stream_lines_min": 32.0,
    "observed_stream_lines_max": 32.0,
    "observed_bars_mean": 14.3,
    "observed_bars_min": 0.0,
    "observed_bars_max": 30.0,
    "validated_bars_mean": 14.3,
    "validated_bars_min": 0.0,
    "validated_bars_max": 30.0
  },
  {
    "epoch": 5,
    "n": 10,
    "rewards_path": "data/processed/notagen/reward_exports/large_sft10_cached10_rewards_refactored_20260626/epoch05_rewards.jsonl",
    "total_reward_mean": 2.9755541738137214,
    "total_reward_min": 1.110614224137931,
    "total_reward_max": 8.196334134615384,
    "parse_reward_mean": 1.0,
    "parse_reward_min": 1.0,
    "parse_reward_max": 1.0,
    "countdown_reward_mean": 1.0,
    "countdown_reward_min": 1.0,
    "countdown_reward_max": 1.0,
    "line_closure_reward_mean": 0.965625,
    "line_closure_reward_min": 0.9375,
    "line_closure_reward_max": 1.0,
    "bar_token_reward_mean": 0.975,
    "bar_token_reward_min": 0.9375,
    "bar_token_reward_max": 1.0,
    "meter_alignment_reward_mean": 0.15162273771225218,
    "meter_alignment_reward_min": 0.0,
    "meter_alignment_reward_max": 0.4673913043478261,
    "meter_duration_closeness_reward_mean": 0.4292724107060433,
    "meter_duration_closeness_reward_min": 0.33870967741935476,
    "meter_duration_closeness_reward_max": 0.5561594202898551,
    "bar_meter_consistency_reward_mean": 0.3683467741935484,
    "bar_meter_consistency_reward_min": 0.0,
    "bar_meter_consistency_reward_max": 1.0,
    "bar_count_reward_mean": 0.359375,
    "bar_count_reward_min": 0.0,
    "bar_count_reward_max": 0.96875,
    "root_similarity_reward_mean": 0.13125,
    "root_similarity_reward_min": 0.03125,
    "root_similarity_reward_max": 0.25,
    "bass_pitch_class_reward_mean": 0.178125,
    "bass_pitch_class_reward_min": 0.0,
    "bass_pitch_class_reward_max": 0.34375,
    "cadence_root_reward_mean": 0.05,
    "cadence_root_reward_min": 0.0,
    "cadence_root_reward_max": 0.25,
    "cadence_bass_reward_mean": 0.3,
    "cadence_bass_reward_min": 0.0,
    "cadence_bass_reward_max": 0.75,
    "observed_stream_lines_mean": 32.0,
    "observed_stream_lines_min": 32.0,
    "observed_stream_lines_max": 32.0,
    "observed_bars_mean": 11.5,
    "observed_bars_min": 0.0,
    "observed_bars_max": 31.0,
    "validated_bars_mean": 11.5,
    "validated_bars_min": 0.0,
    "validated_bars_max": 31.0
  },
  {
    "epoch": 6,
    "n": 10,
    "rewards_path": "data/processed/notagen/reward_exports/large_sft10_cached10_rewards_refactored_20260626/epoch06_rewards.jsonl",
    "total_reward_mean": 3.730641747443859,
    "total_reward_min": 1.0954326923076922,
    "total_reward_max": 7.506620065789474,
    "parse_reward_mean": 1.0,
    "parse_reward_min": 1.0,
    "parse_reward_max": 1.0,
    "countdown_reward_mean": 1.0,
    "countdown_reward_min": 1.0,
    "countdown_reward_max": 1.0,
    "line_closure_reward_mean": 0.95,
    "line_closure_reward_min": 0.84375,
    "line_closure_reward_max": 1.0,
    "bar_token_reward_mean": 0.971875,
    "bar_token_reward_min": 0.90625,
    "bar_token_reward_max": 1.0,
    "meter_alignment_reward_mean": 0.2891788918994949,
    "meter_alignment_reward_min": 0.0,
    "meter_alignment_reward_max": 0.921875,
    "meter_duration_closeness_reward_mean": 0.5866767713589837,
    "meter_duration_closeness_reward_min": 0.3547830374753452,
    "meter_duration_closeness_reward_max": 0.9739583333333334,
    "bar_meter_consistency_reward_mean": 0.4897177419354839,
    "bar_meter_consistency_reward_min": 0.0,
    "bar_meter_consistency_reward_max": 1.0,
    "bar_count_reward_mean": 0.48125,
    "bar_count_reward_min": 0.0,
    "bar_count_reward_max": 0.96875,
    "root_similarity_reward_mean": 0.14375,
    "root_similarity_reward_min": 0.09375,
    "root_similarity_reward_max": 0.21875,
    "bass_pitch_class_reward_mean": 0.2125,
    "bass_pitch_class_reward_min": 0.03125,
    "bass_pitch_class_reward_max": 0.4375,
    "cadence_root_reward_mean": 0.125,
    "cadence_root_reward_min": 0.0,
    "cadence_root_reward_max": 0.5,
    "cadence_bass_reward_mean": 0.375,
    "cadence_bass_reward_min": 0.0,
    "cadence_bass_reward_max": 0.75,
    "observed_stream_lines_mean": 32.0,
    "observed_stream_lines_min": 32.0,
    "observed_stream_lines_max": 32.0,
    "observed_bars_mean": 15.4,
    "observed_bars_min": 0.0,
    "observed_bars_max": 31.0,
    "validated_bars_mean": 15.4,
    "validated_bars_min": 0.0,
    "validated_bars_max": 31.0
  },
  {
    "epoch": 7,
    "n": 10,
    "rewards_path": "data/processed/notagen/reward_exports/large_sft10_cached10_rewards_refactored_20260626/epoch07_rewards.jsonl",
    "total_reward_mean": 3.14588860102795,
    "total_reward_min": 1.0526041666666668,
    "total_reward_max": 9.221565934065934,
    "parse_reward_mean": 0.9,
    "parse_reward_min": 0.0,
    "parse_reward_max": 1.0,
    "countdown_reward_mean": 1.0,
    "countdown_reward_min": 1.0,
    "countdown_reward_max": 1.0,
    "line_closure_reward_mean": 0.96875,
    "line_closure_reward_min": 0.90625,
    "line_closure_reward_max": 1.0,
    "bar_token_reward_mean": 0.971875,
    "bar_token_reward_min": 0.90625,
    "bar_token_reward_max": 1.0,
    "meter_alignment_reward_mean": 0.1665399365874399,
    "meter_alignment_reward_min": 0.0,
    "meter_alignment_reward_max": 0.5714285714285714,
    "meter_duration_closeness_reward_mean": 0.46193653144982666,
    "meter_duration_closeness_reward_min": 0.28472222222222227,
    "meter_duration_closeness_reward_max": 0.7049731182795697,
    "bar_meter_consistency_reward_mean": 0.3463709677419355,
    "bar_meter_consistency_reward_min": 0.0,
    "bar_meter_consistency_reward_max": 1.0,
    "bar_count_reward_mean": 0.34375,
    "bar_count_reward_min": 0.0,
    "bar_count_reward_max": 1.0,
    "root_similarity_reward_mean": 0.159375,
    "root_similarity_reward_min": 0.09375,
    "root_similarity_reward_max": 0.21875,
    "bass_pitch_class_reward_mean": 0.225,
    "bass_pitch_class_reward_min": 0.125,
    "bass_pitch_class_reward_max": 0.3125,
    "cadence_root_reward_mean": 0.175,
    "cadence_root_reward_min": 0.0,
    "cadence_root_reward_max": 0.5,
    "cadence_bass_reward_mean": 0.4,
    "cadence_bass_reward_min": 0.0,
    "cadence_bass_reward_max": 0.75,
    "observed_stream_lines_mean": 32.0,
    "observed_stream_lines_min": 32.0,
    "observed_stream_lines_max": 32.0,
    "observed_bars_mean": 11.0,
    "observed_bars_min": 0.0,
    "observed_bars_max": 32.0,
    "validated_bars_mean": 11.0,
    "validated_bars_min": 0.0,
    "validated_bars_max": 32.0
  },
  {
    "epoch": 8,
    "n": 10,
    "rewards_path": "data/processed/notagen/reward_exports/large_sft10_cached10_rewards_refactored_20260626/epoch08_rewards.jsonl",
    "total_reward_mean": 2.8872937531245744,
    "total_reward_min": 1.0493146929824562,
    "total_reward_max": 7.557854055851064,
    "parse_reward_mean": 1.0,
    "parse_reward_min": 1.0,
    "parse_reward_max": 1.0,
    "countdown_reward_mean": 1.0,
    "countdown_reward_min": 1.0,
    "countdown_reward_max": 1.0,
    "line_closure_reward_mean": 0.95625,
    "line_closure_reward_min": 0.875,
    "line_closure_reward_max": 1.0,
    "bar_token_reward_mean": 0.971875,
    "bar_token_reward_min": 0.9375,
    "bar_token_reward_max": 1.0,
    "meter_alignment_reward_mean": 0.16684931424770966,
    "meter_alignment_reward_min": 0.0,
    "meter_alignment_reward_max": 0.5638297872340425,
    "meter_duration_closeness_reward_mean": 0.5022506899183897,
    "meter_duration_closeness_reward_min": 0.28033625730994155,
    "meter_duration_closeness_reward_max": 0.6276595744680851,
    "bar_meter_consistency_reward_mean": 0.3092741935483871,
    "bar_meter_consistency_reward_min": 0.0,
    "bar_meter_consistency_reward_max": 1.0,
    "bar_count_reward_mean": 0.3,
    "bar_count_reward_min": 0.0,
    "bar_count_reward_max": 0.96875,
    "root_similarity_reward_mean": 0.13125,
    "root_similarity_reward_min": 0.09375,
    "root_similarity_reward_max": 0.15625,
    "bass_pitch_class_reward_mean": 0.19375,
    "bass_pitch_class_reward_min": 0.03125,
    "bass_pitch_class_reward_max": 0.28125,
    "cadence_root_reward_mean": 0.1,
    "cadence_root_reward_min": 0.0,
    "cadence_root_reward_max": 0.25,
    "cadence_bass_reward_mean": 0.4,
    "cadence_bass_reward_min": 0.25,
    "cadence_bass_reward_max": 0.5,
    "observed_stream_lines_mean": 32.0,
    "observed_stream_lines_min": 32.0,
    "observed_stream_lines_max": 32.0,
    "observed_bars_mean": 9.6,
    "observed_bars_min": 0.0,
    "observed_bars_max": 31.0,
    "validated_bars_mean": 9.6,
    "validated_bars_min": 0.0,
    "validated_bars_max": 31.0
  },
  {
    "epoch": 9,
    "n": 10,
    "rewards_path": "data/processed/notagen/reward_exports/large_sft10_cached10_rewards_refactored_20260626/epoch09_rewards.jsonl",
    "total_reward_mean": 3.495151594191136,
    "total_reward_min": 1.0270833333333333,
    "total_reward_max": 8.127368951612903,
    "parse_reward_mean": 0.9,
    "parse_reward_min": 0.0,
    "parse_reward_max": 1.0,
    "countdown_reward_mean": 1.0,
    "countdown_reward_min": 1.0,
    "countdown_reward_max": 1.0,
    "line_closure_reward_mean": 0.965625,
    "line_closure_reward_min": 0.9375,
    "line_closure_reward_max": 1.0,
    "bar_token_reward_mean": 0.96875,
    "bar_token_reward_min": 0.9375,
    "bar_token_reward_max": 1.0,
    "meter_alignment_reward_mean": 0.23071220806514622,
    "meter_alignment_reward_min": 0.0,
    "meter_alignment_reward_max": 0.9838709677419355,
    "meter_duration_closeness_reward_mean": 0.4602190841897024,
    "meter_duration_closeness_reward_min": 0.23611111111111113,
    "meter_duration_closeness_reward_max": 0.9838709677419355,
    "bar_meter_consistency_reward_mean": 0.40656586021505375,
    "bar_meter_consistency_reward_min": 0.0,
    "bar_meter_consistency_reward_max": 1.0,
    "bar_count_reward_mean": 0.39375,
    "bar_count_reward_min": 0.0,
    "bar_count_reward_max": 0.96875,
    "root_similarity_reward_mean": 0.125,
    "root_similarity_reward_min": 0.0625,
    "root_similarity_reward_max": 0.1875,
    "bass_pitch_class_reward_mean": 0.23125,
    "bass_pitch_class_reward_min": 0.09375,
    "bass_pitch_class_reward_max": 0.40625,
    "cadence_root_reward_mean": 0.1,
    "cadence_root_reward_min": 0.0,
    "cadence_root_reward_max": 0.25,
    "cadence_bass_reward_mean": 0.275,
    "cadence_bass_reward_min": 0.0,
    "cadence_bass_reward_max": 0.5,
    "observed_stream_lines_mean": 32.0,
    "observed_stream_lines_min": 32.0,
    "observed_stream_lines_max": 32.0,
    "observed_bars_mean": 12.6,
    "observed_bars_min": 0.0,
    "observed_bars_max": 31.0,
    "validated_bars_mean": 12.6,
    "validated_bars_min": 0.0,
    "validated_bars_max": 31.0
  },
  {
    "epoch": 10,
    "n": 10,
    "rewards_path": "data/processed/notagen/reward_exports/large_sft10_cached10_rewards_refactored_20260626/epoch10_rewards.jsonl",
    "total_reward_mean": 3.3999346454168027,
    "total_reward_min": 0.8509672619047619,
    "total_reward_max": 7.751405083955224,
    "parse_reward_mean": 1.0,
    "parse_reward_min": 1.0,
    "parse_reward_max": 1.0,
    "countdown_reward_mean": 1.0,
    "countdown_reward_min": 1.0,
    "countdown_reward_max": 1.0,
    "line_closure_reward_mean": 0.959375,
    "line_closure_reward_min": 0.90625,
    "line_closure_reward_max": 0.96875,
    "bar_token_reward_mean": 0.971875,
    "bar_token_reward_min": 0.9375,
    "bar_token_reward_max": 1.0,
    "meter_alignment_reward_mean": 0.18469631507534098,
    "meter_alignment_reward_min": 0.0,
    "meter_alignment_reward_max": 0.4925373134328358,
    "meter_duration_closeness_reward_mean": 0.44813321214706264,
    "meter_duration_closeness_reward_min": 0.015873015873015872,
    "meter_duration_closeness_reward_max": 0.7786069651741294,
    "bar_meter_consistency_reward_mean": 0.37429435483870965,
    "bar_meter_consistency_reward_min": 0.0,
    "bar_meter_consistency_reward_max": 1.0,
    "bar_count_reward_mean": 0.365625,
    "bar_count_reward_min": 0.0,
    "bar_count_reward_max": 0.96875,
    "root_similarity_reward_mean": 0.140625,
    "root_similarity_reward_min": 0.125,
    "root_similarity_reward_max": 0.1875,
    "bass_pitch_class_reward_mean": 0.2125,
    "bass_pitch_class_reward_min": 0.09375,
    "bass_pitch_class_reward_max": 0.375,
    "cadence_root_reward_mean": 0.1,
    "cadence_root_reward_min": 0.0,
    "cadence_root_reward_max": 0.25,
    "cadence_bass_reward_mean": 0.425,
    "cadence_bass_reward_min": 0.0,
    "cadence_bass_reward_max": 0.75,
    "observed_stream_lines_mean": 32.0,
    "observed_stream_lines_min": 32.0,
    "observed_stream_lines_max": 32.0,
    "observed_bars_mean": 11.7,
    "observed_bars_min": 0.0,
    "observed_bars_max": 31.0,
    "validated_bars_mean": 11.7,
    "validated_bars_min": 0.0,
    "validated_bars_max": 31.0
  }
]